arolla/__init__.py
arolla/arolla.py
arolla/abc/__init__.py
arolla/abc/abc.py
arolla/abc/attr.py
arolla/abc/aux_binding_policy.py
arolla/abc/cancellation.py
arolla/abc/clib.so
arolla/abc/dummy_numpy.py
arolla/abc/expr.py
arolla/abc/expr_substitution.py
arolla/abc/expr_view.py
arolla/abc/expr_visitor.py
arolla/abc/operator.py
arolla/abc/operator_repr.py
arolla/abc/py_object_qtype.py
arolla/abc/qexpr.py
arolla/abc/qtype.py
arolla/abc/signature.py
arolla/abc/utils.py
arolla/derived_qtype/__init__.py
arolla/derived_qtype/clib.so
arolla/derived_qtype/derived_qtype.py
arolla/derived_qtype/operators/__init__.py
arolla/derived_qtype/operators/derived_qtype.py
arolla/derived_qtype/operators/operators_bootstrap_clib.so
arolla/dynamic_deps/__init__.py
arolla/dynamic_deps/libarolla_py_abc_so.so
arolla/dynamic_deps/libarolla_so.so
arolla/dynamic_deps/libarolla_standard_operators_so.so
arolla/dynamic_deps/libbase_so.so
arolla/dynamic_deps/libdecision_forest_so.so
arolla/dynamic_deps/libderived_qtype_so.so
arolla/dynamic_deps/libjagged_shape_so.so
arolla/dynamic_deps/libobjects_so.so
arolla/examples/__init__.py
arolla/examples/gf/__init__.py
arolla/examples/gf/gf.py
arolla/examples/gf/gf127.so
arolla/examples/my_complex/__init__.py
arolla/examples/my_complex/my_complex.py
arolla/examples/my_complex/my_complex_clib.so
arolla/experimental/__init__.py
arolla/experimental/auto_eval_view.py
arolla/experimental/clib.so
arolla/experimental/colab_safe_repr.py
arolla/experimental/dataset.py
arolla/experimental/dense_array_numpy_conversion.py
arolla/experimental/eval_util.py
arolla/experimental/numpy_conversion.py
arolla/experimental/reload.py
arolla/experimental/table.py
arolla/expr/__init__.py
arolla/expr/containers.py
arolla/expr/default_view.py
arolla/expr/expr.py
arolla/ipython/__init__.py
arolla/ipython/start_ipython.py
arolla/jagged_shape/__init__.py
arolla/jagged_shape/clib.so
arolla/jagged_shape/jagged_shape.py
arolla/jagged_shape/types.py
arolla/jagged_shape/operators/__init__.py
arolla-0.0.4.post0.dist-info/METADATA
arolla-0.0.4.post0.dist-info/WHEEL
arolla-0.0.4.post0.dist-info/top_level.txt
arolla-0.0.4.post0.dist-info/RECORD
