Metadata-Version: 2.1
Name: arolla
Version: 0.0.4.post0
Summary: UNKNOWN
Home-page: UNKNOWN
License: UNKNOWN
Platform: UNKNOWN
Requires-Dist: protobuf (<6.0.0dev,>=5.26.1)
